inventree_dymo/__init__.py
inventree_dymo/core.py
inventree_dymo/dymo.py
inventree_dymo/dymo_to_png.py
inventree_dymo_plugin-1.1.1.dist-info/licenses/LICENSE
inventree_dymo_plugin-1.1.1.dist-info/METADATA
inventree_dymo_plugin-1.1.1.dist-info/WHEEL
inventree_dymo_plugin-1.1.1.dist-info/entry_points.txt
inventree_dymo_plugin-1.1.1.dist-info/top_level.txt
inventree_dymo_plugin-1.1.1.dist-info/RECORD
